LICENSE
httpfile/__init__.py
httpfile/py.typed
python_httpfile-0.0.5.2.dist-info/LICENSE
python_httpfile-0.0.5.2.dist-info/METADATA
python_httpfile-0.0.5.2.dist-info/WHEEL
python_httpfile-0.0.5.2.dist-info/RECORD
