Metadata-Version: 2.1
Name: python-httpfile
Version: 0.0.5.2
Summary: Python httpfile.
Home-page: https://github.com/ChenyangGao/web-mount-packs/tree/main/python-module/python-httpfile
License: MIT
Keywords: http,file,wrapper
Author: ChenyangGao
Author-email: wosiwujm@gmail.com
Requires-Python: >=3.10,<4.0
Classifier: Development Status :: 5 - Production/Stable
Classifier: Intended Audience :: Developers
Classifier: License :: OSI Approved :: MIT License
Classifier: Operating System :: OS Independent
Classifier: Programming Language :: Python
Classifier: Programming Language :: Python :: 3
Classifier: Programming Language :: Python :: 3.10
Classifier: Programming Language :: Python :: 3.11
Classifier: Programming Language :: Python :: 3.12
Classifier: Programming Language :: Python :: 3.13
Classifier: Programming Language :: Python :: 3 :: Only
Classifier: Topic :: Software Development
Classifier: Topic :: Software Development :: Libraries
Classifier: Topic :: Software Development :: Libraries :: Python Modules
Requires-Dist: http_response
Requires-Dist: python-asynctools (>=0.0.5)
Requires-Dist: python-filewrap (>=0.2.1)
Requires-Dist: python-property (>=0.0.2)
Requires-Dist: python-urlopen (>=0.0.7.1)
Project-URL: Repository, https://github.com/ChenyangGao/web-mount-packs/tree/main/python-module/python-httpfile
